pythonprogrammersamazingandverygood/__init__.py
pythonprogrammersamazingandverygood-6741.dist-info/METADATA
pythonprogrammersamazingandverygood-6741.dist-info/WHEEL
pythonprogrammersamazingandverygood-6741.dist-info/top_level.txt
pythonprogrammersamazingandverygood-6741.dist-info/RECORD
