Metadata-Version: 2.4
Name: pythonprogrammersamazingandverygood
Version: 6741
Summary: the best module to ever exist
Dynamic: description
Dynamic: description-content-type
Dynamic: summary
